setup.py
collective/__init__.py
collective.uuid.egg-info/PKG-INFO
collective.uuid.egg-info/SOURCES.txt
collective.uuid.egg-info/dependency_links.txt
collective.uuid.egg-info/entry_points.txt
collective.uuid.egg-info/namespace_packages.txt
collective.uuid.egg-info/not-zip-safe
collective.uuid.egg-info/requires.txt
collective.uuid.egg-info/top_level.txt
collective/uuid/__init__.py
collective/uuid/configure.zcml
collective/uuid/interfaces.py
collective/uuid/tests.py
docs/HISTORY.txt
docs/INSTALL.txt
docs/LICENSE.GPL
docs/LICENSE.ZPL
docs/LICENSE.txt
docs/README.txt
docs/TODO.txt