Metadata-Version: 1.0
Name: collective.uuid
Version: 1.0rc1
Summary: RFC 4122 universally unique identifier utility.
Home-page: http://www.openplans.org/projects/vice/
Author: Derek Richardson
Author-email: syndication@derekrichardson.net
License: ZPL,GPL
Keywords: zope uuid
Platform: UNKNOWN
Classifier: Framework :: Zope2
Classifier: Framework :: Zope3
Classifier: Programming Language :: Python
Classifier: Topic :: Software Development :: Libraries :: Python Modules
